ssb_libtest_urb/__init__.py
ssb_libtest_urb/__main__.py
ssb_libtest_urb/functions.py
ssb_libtest_urb/py.typed
ssb_libtest_urb-0.0.1.dist-info/LICENSE
ssb_libtest_urb-0.0.1.dist-info/METADATA
ssb_libtest_urb-0.0.1.dist-info/WHEEL
ssb_libtest_urb-0.0.1.dist-info/entry_points.txt
ssb_libtest_urb-0.0.1.dist-info/RECORD
