Metadata-Version: 2.3
Name: ssb-libtest-urb
Version: 0.0.1
Summary: SSB Libtest Urb
License: MIT
Author: Urban Olsson
Author-email: urb@ssb.no
Requires-Python: >=3.10,<4.0
Classifier: Development Status :: 4 - Beta
Classifier: License :: OSI Approved :: MIT License
Classifier: Programming Language :: Python :: 3
Classifier: Programming Language :: Python :: 3.10
Classifier: Programming Language :: Python :: 3.11
Classifier: Programming Language :: Python :: 3.12
Classifier: Programming Language :: Python :: 3.13
Requires-Dist: click (>=8.0.1)
Project-URL: Changelog, https://github.com/statisticsnorway/ssb-libtest-urb/releases
Project-URL: Documentation, https://statisticsnorway.github.io/ssb-libtest-urb
Project-URL: Homepage, https://github.com/statisticsnorway/ssb-libtest-urb
Project-URL: Repository, https://github.com/statisticsnorway/ssb-libtest-urb
